tttime/__init__.py
tttime/tttime.py
tttime-1.0.5.dist-info/LICENSE
tttime-1.0.5.dist-info/METADATA
tttime-1.0.5.dist-info/WHEEL
tttime-1.0.5.dist-info/top_level.txt
tttime-1.0.5.dist-info/RECORD
