Metadata-Version: 2.1
Name: tttime
Version: 1.0.5
Summary: An implementation of a TTTime in Python.
Home-page: https://github.com/tonyaellie/tttime
Author: tonyaellie
Author-email: tonya@tokia.dev
Classifier: Programming Language :: Python :: 3
Classifier: License :: OSI Approved :: MIT License
Classifier: Operating System :: OS Independent
Requires-Python: >=3.6
License-File: LICENSE
